pd_to_sheet/__init__.py
pd_to_sheet/admin_area_code.py
pd_to_sheet/check_idcard_num.py
pd_to_sheet/ip2Region.py
pd_to_sheet/ip_area.py
pd_to_sheet/ipv6.py
pd_to_sheet/phone.py
pd_to_sheet/to_excel.py
pd_to_sheet/db/MobileArea.db
pd_to_sheet/db/admin_area_code.db
pd_to_sheet/db/ip2region.db
pd_to_sheet/db/ipdata.db
pd_to_sheet-2.0.1.dist-info/licenses/LICENSE
pd_to_sheet-2.0.1.dist-info/METADATA
pd_to_sheet-2.0.1.dist-info/WHEEL
pd_to_sheet-2.0.1.dist-info/top_level.txt
pd_to_sheet-2.0.1.dist-info/RECORD
