Metadata-Version: 2.4
Name: pd_to_sheet
Version: 2.0.1
Summary: 一个将pandas数据框输出到Excel并美化表格的工具。
Author: sgg
Author-email: police@foxmail.com
Classifier: Programming Language :: Python :: 3
Classifier: License :: OSI Approved :: MIT License
Classifier: Operating System :: OS Independent
Requires-Python: >=3.6
License-File: LICENSE
Requires-Dist: pandas
Requires-Dist: xlsxwriter
Requires-Dist: openpyxl
Requires-Dist: sqlalchemy
Dynamic: author
Dynamic: author-email
Dynamic: classifier
Dynamic: description-content-type
Dynamic: license-file
Dynamic: requires-dist
Dynamic: requires-python
Dynamic: summary
